chromahackerweb/.DS_Store
chromahackerweb/__main__.py
chromahackerweb/static/script.js
chromahackerweb/static/style.css
chromahackerweb/templates/index.html
chromahackerweb/wezterm_import.py
chromahackerweb-0.2.0.dist-info/METADATA
chromahackerweb-0.2.0.dist-info/WHEEL
chromahackerweb-0.2.0.dist-info/entry_points.txt
chromahackerweb-0.2.0.dist-info/RECORD
