Metadata-Version: 2.1
Name: chromahackerweb
Version: 0.2.0
Summary: 
Author: FaunuX
Author-email: judahpspiegel@gmail.com
Requires-Python: >=3.11,<4.0
Classifier: Programming Language :: Python :: 3
Classifier: Programming Language :: Python :: 3.11
Requires-Dist: chromahacker (>=0.3.0,<0.4.0)
Requires-Dist: flask (>=2.3.2,<3.0.0)
